README.md
setup.cfg
setup.py
Blue_DiscordBot.egg-info/PKG-INFO
Blue_DiscordBot.egg-info/SOURCES.txt
Blue_DiscordBot.egg-info/dependency_links.txt
Blue_DiscordBot.egg-info/entry_points.txt
Blue_DiscordBot.egg-info/requires.txt
Blue_DiscordBot.egg-info/top_level.txt
bluebot/__init__.py
bluebot/__main__.py
bluebot/launcher.py
bluebot/logging.py
bluebot/meta.py
bluebot/setup.py
bluebot/core/__init__.py
bluebot/core/bot.py
bluebot/core/checks.py
bluebot/core/cli.py
bluebot/core/config.py
bluebot/core/core_commands.py
bluebot/core/data_manager.py
bluebot/core/developer.py
bluebot/core/errors.py
bluebot/core/events.py
bluebot/core/feature.py
bluebot/core/global_checks.py
bluebot/core/i18n.py
bluebot/core/json_io.py
bluebot/core/rpc.py
bluebot/core/commands/__init__.py
bluebot/core/commands/commands.py
bluebot/core/commands/context.py
bluebot/core/commands/converter.py
bluebot/core/commands/errors.py
bluebot/core/commands/help.py
bluebot/core/commands/requires.py
bluebot/core/downloader/__init__.py
bluebot/core/downloader/checks.py
bluebot/core/downloader/converters.py
bluebot/core/downloader/downloader.py
bluebot/core/downloader/errors.py
bluebot/core/downloader/installable.py
bluebot/core/downloader/json_mixins.py
bluebot/core/downloader/log.py
bluebot/core/downloader/repo_manager.py
bluebot/core/drivers/__init__.py
bluebot/core/drivers/red_base.py
bluebot/core/drivers/red_json.py
bluebot/core/drivers/red_mongo.py
bluebot/core/utils/__init__.py
bluebot/core/utils/antispam.py
bluebot/core/utils/caching.py
bluebot/core/utils/chat_formatting.py
bluebot/core/utils/common_filters.py
bluebot/core/utils/embed.py
bluebot/core/utils/menus.py
bluebot/core/utils/mod.py
bluebot/core/utils/predicates.py
bluebot/core/utils/safety.py
bluebot/core/utils/tunnel.py
bluebot/feature/__init__.py